thg_probability
