Metadata-Version: 1.0
Name: thg-probability
Version: 1.4
Summary: Gaussian and Binomial distributions
Home-page: UNKNOWN
Author: Thomas Hatting
Author-email: mail@thomashatting.co
License: UNKNOWN
Platform: UNKNOWN
